extrai/__init__.py
extrai/core/__init__.py
extrai/core/analytics_collector.py
extrai/core/base_llm_client.py
extrai/core/db_writer.py
extrai/core/errors.py
extrai/core/example_json_generator.py
extrai/core/json_consensus.py
extrai/core/prompt_builder.py
extrai/core/schema_inspector.py
extrai/core/sqlalchemy_hydrator.py
extrai/core/sqlmodel_generator.py
extrai/core/workflow_orchestrator.py
extrai/llm_providers/__init__.py
extrai/llm_providers/deepseek_client.py
extrai/llm_providers/gemini_client.py
extrai/llm_providers/generic_openai_client.py
extrai/llm_providers/huggingface_client.py
extrai/llm_providers/ollama_client.py
extrai/llm_providers/openai_client.py
extrai/utils/__init__.py
extrai/utils/flattening_utils.py
extrai/utils/json_validation_utils.py
extrai/utils/llm_output_processing.py
extrai_workflow-1.0.1.dist-info/licenses/LICENSE
extrai_workflow-1.0.1.dist-info/METADATA
extrai_workflow-1.0.1.dist-info/WHEEL
extrai_workflow-1.0.1.dist-info/top_level.txt
extrai_workflow-1.0.1.dist-info/RECORD
