Metadata-Version: 2.4
Name: extrai-workflow
Version: 1.0.1
Summary: Structured data extraction with LLM majority vote
Author-email: Elias Thouant <elias.thouant@gmail.com>
Project-URL: Homepage, https://github.com/Telsho/Extrai
License-File: LICENSE
Requires-Dist: jsonschema==4.25.1
Requires-Dist: openai==2.9.0
Requires-Dist: pydantic==2.12.5
Requires-Dist: sqlalchemy==2.0.44
Requires-Dist: sqlmodel==0.0.27
Provides-Extra: dev
Requires-Dist: pytest; extra == "dev"
Requires-Dist: aiofiles; extra == "dev"
Requires-Dist: pytest-asyncio; extra == "dev"
Requires-Dist: ruff; extra == "dev"
Requires-Dist: coverage; extra == "dev"
Requires-Dist: sphinx; extra == "dev"
Requires-Dist: furo; extra == "dev"
Requires-Dist: sphinx-copybutton; extra == "dev"
Requires-Dist: sphinxcontrib-mermaid; extra == "dev"
Requires-Dist: build; extra == "dev"
Requires-Dist: twine; extra == "dev"
Dynamic: license-file
